ycleptic/__init__.py
ycleptic/cli.py
ycleptic/dictthings.py
ycleptic/makedoc.py
ycleptic/stringthings.py
ycleptic/walkers.py
ycleptic/yclept.py
ycleptic/resources/__init__.py
ycleptic/resources/example_base.yaml
ycleptic-2.0.3.dist-info/METADATA
ycleptic-2.0.3.dist-info/WHEEL
ycleptic-2.0.3.dist-info/entry_points.txt
ycleptic-2.0.3.dist-info/licenses/LICENSE
ycleptic-2.0.3.dist-info/RECORD
