Metadata-Version: 2.4
Name: ycleptic
Version: 2.0.3
Summary: A YAML-format configuration generator
Project-URL: Source, https://github.com/cameronabrams/ycleptic
Project-URL: Documentation, https://ycleptic.readthedocs.io/en/latest/
Project-URL: Bug Tracker, https://github.com/cameronabrams/ycleptic/issues
Author-email: Cameron F Abrams <cfa22@drexel.edu>
License-File: LICENSE
Classifier: License :: OSI Approved :: MIT License
Classifier: Operating System :: OS Independent
Classifier: Programming Language :: Python :: 3
Requires-Python: >=3.7
Requires-Dist: pyyaml>=6
